pyjibe/__init__.py
pyjibe/__main__.py
pyjibe/_version.py
pyjibe/colormap.py
pyjibe/extensions.py
pyjibe/registry.py
pyjibe/units.py
pyjibe/util.py
pyjibe/fd/__init__.py
pyjibe/fd/dlg_autosave_design.ui
pyjibe/fd/dlg_export_vals.py
pyjibe/fd/dlg_export_vals.ui
pyjibe/fd/export.py
pyjibe/fd/main.py
pyjibe/fd/main.ui
pyjibe/fd/mpl_edelta.py
pyjibe/fd/mpl_indent.py
pyjibe/fd/mpl_preproc.py
pyjibe/fd/mpl_qmap.py
pyjibe/fd/rating_base.py
pyjibe/fd/rating_iface.py
pyjibe/fd/rating_iface.ui
pyjibe/fd/tab_edelta.py
pyjibe/fd/tab_edelta.ui
pyjibe/fd/tab_fit.py
pyjibe/fd/tab_fit.ui
pyjibe/fd/tab_info.py
pyjibe/fd/tab_info.ui
pyjibe/fd/tab_preprocess.py
pyjibe/fd/tab_preprocess.ui
pyjibe/fd/tab_qmap.py
pyjibe/fd/tab_qmap.ui
pyjibe/fd/widget_plot_fd.py
pyjibe/fd/widget_plot_preproc.py
pyjibe/fd/widget_preprocess_item.py
pyjibe/fd/widget_preprocess_item.ui
pyjibe/head/__init__.py
pyjibe/head/dlg_tool_convert.py
pyjibe/head/dlg_tool_convert.ui
pyjibe/head/infdoubleslider.py
pyjibe/head/infdoublespinbox.py
pyjibe/head/main.py
pyjibe/head/main.ui
pyjibe/head/preferences.py
pyjibe/head/preferences.ui
pyjibe/head/update.py
pyjibe/head/custom_widgets/__init__.py
pyjibe/head/custom_widgets/dirdialog_multiselect.py
pyjibe/head/custom_widgets/mpl_navigation_toolbar_icons.py
pyjibe/head/custom_widgets/wait_cursor.py
pyjibe/img/icon.png
pyjibe/img/icon.svg
pyjibe/img/savedat.svg
pyjibe/img/savedat_large.png
pyjibe/img/saveimg.svg
pyjibe/img/saveimg_large.png
pyjibe/img/splash.png
pyjibe/img/splash.svg
pyjibe-0.16.1.dist-info/licenses/LICENSE
pyjibe-0.16.1.dist-info/METADATA
pyjibe-0.16.1.dist-info/WHEEL
pyjibe-0.16.1.dist-info/entry_points.txt
pyjibe-0.16.1.dist-info/top_level.txt
pyjibe-0.16.1.dist-info/RECORD
