Metadata-Version: 2.4
Name: pyjibe
Version: 0.16.1
Summary: Graphical user interface for Bio-AFM analysis
Author: Eoghan O'Connell, Paul Müller
Maintainer-email: Paul Müller <dev@craban.de>
License: GPL version 3.0 or later
Project-URL: source, https://github.com/AFM-analysis/PyJibe
Project-URL: tracker, https://github.com/AFM-analysis/PyJibe/Issues
Project-URL: documentation, https://pyjibe.readthedocs.io/en/stable/
Project-URL: changelog, https://pyjibe.readthedocs.io/en/stable/sec_changelog.html
Keywords: atomic force microscopy,biomechanics
Classifier: Operating System :: OS Independent
Classifier: Programming Language :: Python :: 3
Classifier: Topic :: Scientific/Engineering :: Visualization
Classifier: Intended Audience :: Science/Research
Requires-Python: <4,>=3.10
License-File: LICENSE
Requires-Dist: afmformats>=0.18.0
Requires-Dist: nanite>=4.2.1
Requires-Dist: matplotlib<3.7.5,>=3
Requires-Dist: packaging
Requires-Dist: pyqt6
Dynamic: license-file
